dryptopy/__init__.py
dryptopy/functions.py
dryptopy-0.0.6.dist-info/LICENSE
dryptopy-0.0.6.dist-info/METADATA
dryptopy-0.0.6.dist-info/WHEEL
dryptopy-0.0.6.dist-info/top_level.txt
dryptopy-0.0.6.dist-info/RECORD
