Metadata-Version: 2.1
Name: dryptopy
Version: 0.0.6
Summary: A package containing functions to be used in cryptocurreny trading
Home-page: https://github.com/dryptopy/dryptopy-api
Author: Dryptopy
Author-email: dryptopy@protonmail.com
License: UNKNOWN
Project-URL: Bug Tracker, https://github.com/dryptopy/dryptopy-api/issues
Platform: UNKNOWN
Classifier: Programming Language :: Python :: 3
Classifier: License :: OSI Approved :: MIT License
Classifier: Operating System :: OS Independent
Requires-Python: >=3.6
License-File: LICENSE
